Metadata-Version: 2.1
Name: pydefang
Version: 0.0.1
Summary: A defang/refang utility written in Python.
Home-page: https://github.com/0x3a/pydefang
Author: Yonathan Klijnsma
Author-email: admin@0x3a.com
License: UNKNOWN
Platform: UNKNOWN
Requires-Python: >=3
